{
  "days": {
    "monday": {
      "title": "Maanantai",
      "tasks": [
        "Kyykyt 4 × 15",
        "Askelkyykyt 3 × 12 kummallakin",
        "Hyppynarua 4 min"
      ]
    },
    "tuesday": {
      "title": "Tiistai",
      "tasks": [
        "Mailankäsittely 10 min: nopeat siirrot ja taaksepäin",
        "Liikkuvuus: lonkat ja reidet 10 min"
      ]
    },
    "wednesday": {
      "title": "Keskiviikko",
      "tasks": [
        "Punnerrukset 4 × 15",
        "Dipsit 3 × 10",
        "Vatsalihas: 3 × 20 rutistusta",
        "Sivulankku 3 × 30 sek"
      ]
    },
    "thursday": {
      "title": "Torstai",
      "tasks": [
        "Intervallijuoksu: 8 × 30 sek täysillä + 30 sek kävely",
        "Venyttely koko keho 10 min"
      ]
    },
    "friday": {
      "title": "Perjantai",
      "tasks": [
        "Lankku 3 × 45 sek",
        "Selkälihakset: 3 × 15",
        "Hyppykyykyt 3 × 10"
      ]
    },
    "saturday": {
      "title": "Lauantai",
      "tasks": [
        "Aerobinen: pyöräily tai uinti 50 min"
      ]
    },
    "sunday": {
      "title": "Sunnuntai",
      "tasks": [
        "Lepopäivä"
      ]
    }
  }
}
